{"rabbit_version":"3.6.10","users":[{"name":"guest","password_hash":"Ctox9ZorCzSeBIi8s5xFpAeocAenhxc4CsTFJKVJWHNKEbCx","hashing_algorithm":"rabbit_password_hashing_sha256","tags":"administrator"}],"vhosts":[{"name":"/"}],"permissions":[{"user":"guest","vhost":"/","configure":".*","write":".*","read":".*"}],"parameters":[],"global_parameters":[{"name":"cluster_name","value":"rabbit@rabbitmq"}],"policies":[],"queues":[{"name":"meta.deployment.irhandled","vhost":"/","durable":false,"auto_delete":false,"arguments":{}},{"name":"meta.deployment.compiled","vhost":"/","durable":false,"auto_delete":false,"arguments":{}},{"name":"meta.production.recieveddata","vhost":"/","durable":false,"auto_delete":false,"arguments":{}},{"name":"meta.deployment.irtransformed","vhost":"/","durable":false,"auto_delete":false,"arguments":{}}],"exchanges":[{"name":"meta.deployment","vhost":"/","type":"topic","durable":true,"auto_delete":false,"internal":false,"arguments":{}},{"name":"meta.production","vhost":"/","type":"topic","durable":true,"auto_delete":false,"internal":false,"arguments":{}}],"bindings":[{"source":"meta.deployment","vhost":"/","destination":"meta.deployment.compiled","destination_type":"queue","routing_key":"compiled","arguments":{}},{"source":"meta.deployment","vhost":"/","destination":"meta.deployment.irhandled","destination_type":"queue","routing_key":"irhandled","arguments":{}},{"source":"meta.deployment","vhost":"/","destination":"meta.deployment.irtransformed","destination_type":"queue","routing_key":"irtransformed","arguments":{}},{"source":"meta.production","vhost":"/","destination":"meta.production.recieveddata","destination_type":"queue","routing_key":"recieveddata","arguments":{}}]}